faceserve/__init__.py
faceserve-0.0.0.dist-info/LICENSE
faceserve-0.0.0.dist-info/METADATA
faceserve-0.0.0.dist-info/WHEEL
faceserve-0.0.0.dist-info/top_level.txt
faceserve-0.0.0.dist-info/zip-safe
faceserve-0.0.0.dist-info/RECORD
