Metadata-Version: 2.1
Name: faceserve
Version: 0.0.0
Summary: Face recognition serving APIs
Home-page: https://gitlab.com/hieupth/pyfaceserve
Author: Hieu Pham
Author-email: 64821726+hieupth@users.noreply.github.com
License: Copyright (c) 2024 Hieu Pham
Classifier: Development Status :: 1 - Planning
Classifier: Intended Audience :: Developers
Classifier: Topic :: Software Development :: Build Tools
Classifier: Programming Language :: Python :: 3
License-File: LICENSE
